[
    {
        "id": 1,
        "title": "Docker",
        "category": "Conteneurisation",
        "image": "https://elearning.rousseltm.fr/admin/images/formations/1/1.jpg",
        "views": 790472
    },
    {
        "id": 2,
        "title": "Dynatrace",
        "category": "observabilité",
        "image": "https://elearning.rousseltm.fr/admin/images/formations/2/2.jpg",
        "views": 685102
    },
    {
        "id": 3,
        "title": "Vagrant",
        "category": "Automatisation",
        "image": "https://elearning.rousseltm.fr/admin/images/formations/3/3.jpg",
        "views": 5102
    },
    {
        "id": 11,
        "title": "Grafana",
        "category": "observabilité",
        "image": "https://elearning.rousseltm.fr/admin/images/formations/11/11.jpg",
        "views": 836745
    }
]
